covira/__init__.py
covira/covira.py
covira-1.1.12.dist-info/LICENSE
covira-1.1.12.dist-info/METADATA
covira-1.1.12.dist-info/WHEEL
covira-1.1.12.dist-info/top_level.txt
covira-1.1.12.dist-info/RECORD
