Metadata-Version: 2.1
Name: covira
Version: 1.1.12
Summary: CoVIRA (Consensus by Voting with Iterative Re-weighting based on Agreement)
Home-page: UNKNOWN
Author: Frederico Schmitt Kremer
Author-email: fred.s.kremer@gmail.com
License: UNKNOWN
Project-URL: Source Code, https://github.com/fredericokremer/covira
Keywords: bioinformatics machine-learning data science
Platform: UNKNOWN
Requires-Dist: numpy
Requires-Dist: pandas
